tenda_everest/__init__.py
tenda_everest/main.py
tenda_everest/package.py
tenda_everest-0.3.1.dist-info/LICENSE
tenda_everest-0.3.1.dist-info/METADATA
tenda_everest-0.3.1.dist-info/WHEEL
tenda_everest-0.3.1.dist-info/top_level.txt
tenda_everest-0.3.1.dist-info/RECORD
