Metadata-Version: 2.1
Name: tenda-everest
Version: 0.3.1
Summary: Python package to manage Tenda Everest router
Home-page: https://github.com/quillcraftsman/tenda-everest
Author: quillcraftsman
Author-email: quill@craftsman.lol
License: MIT
Project-URL: Documentation, https://quillcraftsman.github.io/tenda-everest
Project-URL: Source, https://github.com/quillcraftsman/tenda-everest
Project-URL: Tracker, https://github.com/quillcraftsman/tenda-everest/issues
Project-URL: Release notes, https://github.com/quillcraftsman/tenda-everest/releases
Project-URL: Changelog, https://github.com/quillcraftsman/tenda-everest/releases
Project-URL: Download, https://pypi.org/project/tenda-everest/
Keywords: python,package,everest,tenda,router,manage
Classifier: Development Status :: 3 - Alpha
Classifier: Intended Audience :: Developers
Classifier: License :: OSI Approved :: MIT License
Classifier: Programming Language :: Python :: 3
Classifier: Environment :: Other Environment
Classifier: Operating System :: OS Independent
Classifier: Topic :: Software Development
Classifier: Topic :: Communications
Classifier: Topic :: Internet
Classifier: Topic :: Security
Classifier: Topic :: System :: Networking
Requires-Python: >=3
License-File: LICENSE
